Workbook

Sheet Raw_Data
A1: Metric | B1: 2021 | C1: 2022 | D1: 2023 | E1: 2024 | F1: 2025
A2: Revenue | B2: 44538 | C2: 46710 | D2: 51217 | E2: 51368 | F2: 46309
A3: Gross Profit | B3: 19962 | C3: 21479 | D3: 22292 | E3: 22887 | F3: 19790
A4: Operating Income | B4: 6937 | C4: 6675 | D4: 5915 | E4: 6311 | F4: 3702
A5: Net Income | B5: 5727 | C5: 6046 | D5: 5070 | E5: 5700 | F5: 3219
A6: Cash | B6: 13476 | C6: 12997 | D6: 10675 | E6: 11582 | F6: 9151
A7: Accounts Receivable | B7: 4463 | C7: 4667 | D7: 4131 | E7: 4427 | F7: 4717
A8: Inventory | B8: 6854 | C8: 8420 | D8: 8454 | E8: 7519 | F8: 7489
A9: Accounts Payable | B9: 2836 | C9: 3358 | D9: 2862 | E9: 2851 | F9: 3479
A10: Total Assets | B10: 36579 | C10: 40321 | D10: 37531 | E10: 38110 | F10: 36579
A11: Total Debt | B11: 9880 | C11: 12619 | D11: 12138 | E11: 11977 | F11: 11016
A12: Shareholders' Equity | B12: 12767 | C12: 15281 | D12: 14004 | E12: 14430 | F12: 13213
... A14: Capital Expenditure | B14: 695 | C14: 758 | D14: 969 | E14: 812 | F14: 430

Sheet Assumptions
A1: Assumption | B1: Base Case
A2: Revenue Growth 2026 | B2: 0.05
A3: Revenue Growth 2027 | B3: 0.06
A4: Revenue Growth 2028 | B4: 0.07
A5: Gross Margin | B5: 0.44
A6: Operating Margin | B6: 0.1
A7: Tax Rate | B7: 0.2
A8: Capex % Revenue | B8: 0.015
A9: AR Days | B9: 35
A10: Inventory Days | B10: 100
A11: AP Days | B11: 45

Sheet Ratios
A1: Ratio | B1: 2021 | C1: 2022 | D1: 2023 | E1: 2024 | F1: 2025
A2: Gross Margin | B2: =Raw_Data!B3/Raw_Data!B2 -> 0.44820154 | C2: =Raw_Data!C3/Raw_Data!C2 -> 0.45983729 | D2: =Raw_Data!D3/Raw_Data!D2 -> 0.43524611 | E2: =Raw_Data!E3/Raw_Data!E2 -> 0.44554976 | F2: =Raw_Data!F3/Raw_Data!F2 -> 0.42734674
A3: Operating Margin | B3: =Raw_Data!B4/Raw_Data!B2 -> 0.15575464 | C3: =Raw_Data!C4/Raw_Data!C2 -> 0.14290302 | D3: =Raw_Data!D4/Raw_Data!D2 -> 0.115489 | E3: =Raw_Data!E4/Raw_Data!E2 -> 0.12285859 | F3: =Raw_Data!F4/Raw_Data!F2 -> 0.079941264
A4: Net Margin | B4: =Raw_Data!B5/Raw_Data!B2 -> 0.12858682 | C4: =Raw_Data!C5/Raw_Data!C2 -> 0.12943695 | D4: =Raw_Data!D5/Raw_Data!D2 -> 0.09899057 | E4: =Raw_Data!E5/Raw_Data!E2 -> 0.11096402 | F4: =Raw_Data!F5/Raw_Data!F2 -> 0.069511326
A5: ROA | B5: =Raw_Data!B5/Raw_Data!B10 -> 0.15656524 | C5: =Raw_Data!C5/Raw_Data!C10 -> 0.14994668 | D5: =Raw_Data!D5/Raw_Data!D10 -> 0.13508833 | E5: =Raw_Data!E5/Raw_Data!E10 -> 0.14956704 | F5: =Raw_Data!F5/Raw_Data!F10 -> 0.088001312
A6: ROE | B6: =Raw_Data!B5/Raw_Data!B12 -> 0.44857837 | C6: =Raw_Data!C5/Raw_Data!C12 -> 0.39565473 | D6: =Raw_Data!D5/Raw_Data!D12 -> 0.36203942 | E6: =Raw_Data!E5/Raw_Data!E12 -> 0.3950104 | F6: =Raw_Data!F5/Raw_Data!F12 -> 0.2436237
A7: Debt / Equity | B7: =Raw_Data!B11/Raw_Data!B12 -> 0.77387013 | C7: =Raw_Data!C11/Raw_Data!C12 -> 0.82579674 | D7: =Raw_Data!D11/Raw_Data!D12 -> 0.86675236 | E7: =Raw_Data!E11/Raw_Data!E12 -> 0.83000693 | F7: =Raw_Data!F11/Raw_Data!F12 -> 0.83372436
A8: Cash Conversion Ratio | B8: =Raw_Data!B13/Raw_Data!B5 -> 1.1623887 | C8: =Raw_Data!C13/Raw_Data!C5 -> 0.85808799 | D8: =Raw_Data!D13/Raw_Data!D5 -> 1.152071 | E8: =Raw_Data!E13/Raw_Data!E5 -> 1.3033333 | F8: =Raw_Data!F13/Raw_Data!F5 -> 1.148804
A9: Free Cash Flow | B9: =Raw_Data!B13-Raw_Data!B14 -> 5962 | C9: =Raw_Data!C13-Raw_Data!C14 -> 4430 | D9: =Raw_Data!D13-Raw_Data!D14 -> 4872 | E9: =Raw_Data!E13-Raw_Data!E14 -> 6617 | F9: =Raw_Data!F13-Raw_Data!F14 -> 3268
A10: Receivable Days | B10: =(Raw_Data!B7/Raw_Data!B2)*365 -> 36.575396 | C10: =(Raw_Data!C7/Raw_Data!C2)*365 -> 36.468743 | D10: =(Raw_Data!D7/Raw_Data!D2)*365 -> 29.439737 | E10: =(Raw_Data!E7/Raw_Data!E2)*365 -> 31.456451 | F10: =(Raw_Data!F7/Raw_Data!F2)*365 -> 37.178626
A11: Inventory Days | B11: =(Raw_Data!B8/(Raw_Data!B2-Raw_Data!B3))*365 -> 101.79484 | C11: =(Raw_Data!C8/(Raw_Data!C2-Raw_Data!C3))*365 -> 121.80651 | D11: =(Raw_Data!D8/(Raw_Data!D2-Raw_Data!D3))*365 -> 106.67969 | E11: =(Raw_Data!E8/(Raw_Data!E2-Raw_Data!E3))*365 -> 96.360205 | F11: =(Raw_Data!F8/(Raw_Data!F2-Raw_Data!F3))*365 -> 103.07647
A12: Payable Days | B12: =(Raw_Data!B9/(Raw_Data!B2-Raw_Data!B3))*365 -> 42.119954 | C12: =(Raw_Data!C9/(Raw_Data!C2-Raw_Data!C3))*365 -> 48.57794 | D12: =(Raw_Data!D9/(Raw_Data!D2-Raw_Data!D3))*365 -> 36.115125 | E12: =(Raw_Data!E9/(Raw_Data!E2-Raw_Data!E3))*365 -> 36.537165 | F12: =(Raw_Data!F9/(Raw_Data!F2-Raw_Data!F3))*365 -> 47.88397
A13: CCC | B13: =B10+B11-B12 -> 96.250282 | C13: =C10+C11-C12 -> 109.69731 | D13: =D10+D11-D12 -> 100.0043 | E13: =E10+E11-E12 -> 91.279491 | F13: =F10+F11-F12 -> 92.37113

Sheet Forecast
A1: Metric | B1: 2025A | C1: 2026E | D1: 2027E | E1: 2028E
A2: Revenue | B2: 46309 | C2: 48624 | D2: 51542 | E2: 55150
A3: Gross Profit | B3: 19790 | C3: 21394 | D3: 22678 | E3: 24266
A4: Operating Income | B4: 3702 | C4: 4862 | D4: 5154 | E4: 5515
A5: Net Income | B5: 3219 | C5: =C4*(1-Assumptions!$B$7) -> 3889.6 | D5: =D4*(1-Assumptions!$B$7) -> 4123.2 | E5: =E4*(1-Assumptions!$B$7) -> 4412
A6: Accounts Recievables | B6: 4717 | C6: =C2*(Assumptions!$B$9/365) -> 4662.5753 | D6: =D2*(Assumptions!$B$9/365) -> 4942.3836 | E6: =E2*(Assumptions!$B$9/365) -> 5288.3562
A7: Inventory | B7: 7489 | C7: =(C2-C3)*(Assumptions!$B$10/365) -> 7460.274 | D7: =(D2-D3)*(Assumptions!$B$10/365) -> 7907.9452 | E7: =(E2-E3)*(Assumptions!$B$10/365) -> 8461.3699
A8: Accounts Payable | B8: 3479 | C8: =(C2-C3)*(Assumptions!$B$11/365) -> 3357.1233 | D8: =(D2-D3)*(Assumptions!$B$11/365) -> 3558.5753 | E8: =(E2-E3)*(Assumptions!$B$11/365) -> 3807.6164
A9: Capex | B9: 430 | C9: =C2*Assumptions!$B$8 -> 729.36 | D9: =D2*Assumptions!$B$8 -> 773.13 | E9: =E2*Assumptions!$B$8 -> 827.25
A10: Free Cash Flow | B10: =B5-B9 -> 2789 | C10: =C5-C9 -> 3160.24 | D10: =D5-D9 -> 3350.07 | E10: =E5-E9 -> 3584.75

Sheet Scenerios
A1: Assumption | B1: Bear | C1: Base | D1: Bull
A2: Revenue Growth 2026 | B2: 0.02 | C2: 0.05 | D2: 0.08
A3: Revenue Growth 2027 | B3: 0.03 | C3: 0.06 | D3: 0.1
A4: Revenue Growth 2028 | B4: 0.04 | C4: 0.07 | D4: 0.12
A5: Operating Margin | B5: 0.08 | C5: 0.1 | D5: 0.12
A6: Revenue 2028 | B6: 50925 | C6: 55150 | D6: 62150
A7: Operating Income 2028 | B7: 4074 | C7: 5515 | D7: 7458
A8: Net Income 2028 | B8: 3259 | C8: 4412 | D8: 5966

Sheet DashBoard
A1: Year | B1: Revenue
A2: 2021 | B2: 44538 | I2: 2021 | J2: 5727
A3: 2022 | B3: 46710 | I3: 2022 | J3: 6046
A4: 2023 | B4: 51217 | I4: 2023 | J4: 5070
A5: 2024 | B5: 51368 | I5: 2024 | J5: 5700
A6: 2025 | B6: 46309 | I6: 2025 | J6: 3219
A7: 2026E | B7: 48624 | I7: 2026E | J7: 3890
A8: 2027E | B8: 51542 | I8: 2027E | J8: 4123
A9: 2028E | B9: 55150 | I9: 2028E | J9: 4412
I17: Scenario | J17: Net Income 2028
A18: 2021 | B18: 5962 | I18: Bear | J18: 3259
A19: 2022 | B19: 4430 | I19: Base | J19: 4412
A20: 2023 | B20: 4872 | I20: Bull | J20: 5966
A21: 2024 | B21: 6617
A22: 2025 | B22: 3268
A23: 2026E | B23: 3160
A24: 2027E | B24: 3350
A25: 2028E | B25: 3585
